irs/__init__.py
irs/__main__.py
irs/cli.py
irs/config.py
irs/manage.py
irs/manager.py
irs/metadata.py
irs/ripper.py
irs/test1.py
irs/utils.py
irs-6.2.2.dist-info/DESCRIPTION.rst
irs-6.2.2.dist-info/METADATA
irs-6.2.2.dist-info/RECORD
irs-6.2.2.dist-info/WHEEL
irs-6.2.2.dist-info/entry_points.txt
irs-6.2.2.dist-info/metadata.json
irs-6.2.2.dist-info/top_level.txt
