Metadata-Version: 2.0
Name: irs
Version: 6.2.2
Summary: A music downloader that just gets metadata.
Home-page: https://github.com/kepoorhampond/irs
Author: Kepoor Hampond
Author-email: kepoorh@gmail.com
License: GPL
Platform: UNKNOWN
Requires-Dist: bs4
Requires-Dist: mutagen
Requires-Dist: requests
Requires-Dist: spotipy
Requires-Dist: youtube-dl
